EntsoeApi_EES/EntsoeApi.py
EntsoeApi_EES/PriceValue.py
EntsoeApi_EES/RestApiBase.py
EntsoeApi_EES/__init__.py
entsoeapi_ees-0.0.1.dist-info/METADATA
entsoeapi_ees-0.0.1.dist-info/WHEEL
entsoeapi_ees-0.0.1.dist-info/licenses/LICENSE
entsoeapi_ees-0.0.1.dist-info/RECORD
