Metadata-Version: 2.3
Name: EntsoeApi_EES
Version: 0.0.1
Summary: A python package to interface with the Entsoe api
Project-URL: Homepage, https://github.com/EES-TUe/entsoe-data-collection
Project-URL: Issues, https://github.com/EES-TUe/entsoe-data-collection/issues
Author-email: Leo van Schooten <l.g.t.v.schooten@tue.nl>
License-File: LICENSE
Classifier: License :: OSI Approved :: MIT License
Classifier: Operating System :: OS Independent
Classifier: Programming Language :: Python :: 3
Requires-Python: >=3.8
Requires-Dist: pandas==2.2.1
Requires-Dist: requests==2.31.0
